multiquests/__init__.py
multiquests/multiquests.py
multiquests-1.0.0.dist-info/LICENSE.txt
multiquests-1.0.0.dist-info/METADATA
multiquests-1.0.0.dist-info/WHEEL
multiquests-1.0.0.dist-info/top_level.txt
multiquests-1.0.0.dist-info/RECORD
