Metadata-Version: 2.1
Name: multiquests
Version: 1.0.0
Summary: A simple crawler framework for multi-coroutine and multi-process
Home-page: https://github.com/Haloherooo/multiquests
Author: Bohan Li
Author-email: lbhllbyz@163.com
License: MIT Licence
Platform: UNKNOWN
Classifier: Development Status :: 2 - Pre-Alpha
Classifier: Operating System :: OS Independent
Classifier: License :: OSI Approved :: MIT License
Classifier: Programming Language :: Python :: 3.5
Classifier: Programming Language :: Python :: 3.6
Classifier: Programming Language :: Python :: 3.7
Classifier: Programming Language :: Python :: 3.8
Classifier: Programming Language :: Python :: 3.9
Classifier: Programming Language :: Python :: 3.10
Classifier: Programming Language :: Python :: 3.11
License-File: LICENSE.txt
Requires-Dist: asyncio
Requires-Dist: aiohttp
Requires-Dist: multiprocessing
Requires-Dist: nest-asyncio
